pelican/plugins/redirect_url/__init__.py
pelican/plugins/redirect_url/redirect_url.py
pelican_redirect_url-0.1.1.dist-info/COPYING
pelican_redirect_url-0.1.1.dist-info/METADATA
pelican_redirect_url-0.1.1.dist-info/WHEEL
pelican_redirect_url-0.1.1.dist-info/top_level.txt
pelican_redirect_url-0.1.1.dist-info/RECORD
