Metadata-Version: 2.1
Name: pelican-redirect-url
Version: 0.1.1
Summary: Pelican plugin to redirect to any URL
Home-page: https://github.com/FriedrichFroebel/pelican-redirect-url/
Author: FriedrichFröbel
License: AGPL-3.0
Keywords: pelican,plugin,redirect
Classifier: Development Status :: 4 - Beta
Classifier: Environment :: Console
Classifier: Framework :: Pelican
Classifier: Framework :: Pelican :: Plugins
Classifier: Intended Audience :: End Users/Desktop
Classifier: License :: OSI Approved :: GNU Affero General Public License v3
Classifier: Operating System :: OS Independent
Classifier: Programming Language :: Python
Classifier: Programming Language :: Python :: 3
Classifier: Programming Language :: Python :: 3 :: Only
Classifier: Topic :: Internet :: WWW/HTTP
Classifier: Topic :: Software Development :: Libraries :: Python Modules
Requires-Python: >=3.7, <4
License-File: COPYING
Provides-Extra: dev
Requires-Dist: flake8 ; extra == 'dev'
Requires-Dist: pep8-naming ; extra == 'dev'
Requires-Dist: pelican (>=4.5) ; extra == 'dev'
Requires-Dist: Markdown ; extra == 'dev'
